README.md
setup.py
gummy/__init__.py
gummy.egg-info/PKG-INFO
gummy.egg-info/SOURCES.txt
gummy.egg-info/dependency_links.txt
gummy.egg-info/entry_points.txt
gummy.egg-info/requires.txt
gummy.egg-info/top_level.txt
gummy/data/ManPortRating.csv
gummy/data/NmapPortRating.csv
gummy/data/OrganizationallyUniqueIdentifier.csv
gummy/data/PortDescription.csv
gummy/data/StatPortRating.csv
gummy/entry_points/__init__.py
gummy/entry_points/gummy_run.py
gummy/modules/__init__.py
gummy/modules/m_scanner.py
gummy/modules/n_scanner.py
gummy/modules/scanner.py
gummy/tools/__init__.py
gummy/tools/arg_pars.py
gummy/tools/config.py
gummy/tools/log.py
gummy/tools/oui_master.py
gummy/tools/parser.py
gummy/tools/port_master.py
gummy/tools/shell.py
gummy/tools/storage.py
gummy/tools/tools.py