Metadata-Version: 2.1
Name: gummy
Version: 0.1.20
Summary: Automated LAN scanner based on masscan and nmap
Home-page: https://github.com/v-yar/gummy
Author: Vladimir Yarmiychuk
Author-email: yarmiychuk@protonmail.com 
License: UNKNOWN
Keywords: security
Platform: UNKNOWN
Classifier: Development Status :: 3 - Alpha
Classifier: Environment :: Console
Classifier: Intended Audience :: Developers
Classifier: Intended Audience :: System Administrators
Classifier: Operating System :: Unix
Classifier: License :: OSI Approved :: MIT License
Classifier: Topic :: Security
Classifier: Topic :: System :: Networking
Classifier: Operating System :: OS Independent
Classifier: Programming Language :: Python
Classifier: Programming Language :: Python :: 3.6
